bibtexentryparser/__init__.py
bibtexentryparser/bibDefinitions.py
bibtexentryparser/bibparser.py
bibtexentryparser/bibwriter.py
bibtexentryparser-1.0.0.dist-info/COPYING
bibtexentryparser-1.0.0.dist-info/METADATA
bibtexentryparser-1.0.0.dist-info/WHEEL
bibtexentryparser-1.0.0.dist-info/top_level.txt
bibtexentryparser-1.0.0.dist-info/RECORD
