Metadata-Version: 2.1
Name: bibtexentryparser
Version: 1.0.0
Summary: Python module to parse BibTeX entries
Home-page: https://github.com/scythja123/python-bitexentryparser
Author: Sonja Stuedli
Author-email: scythja@gmail.com
License: LGPLv3 or BSD
Platform: any
Requires-Python: >=3
